harambe/__init__.py
harambe/cache.py
harambe/cookie_utils.py
harambe/core.py
harambe/handlers.py
harambe/instrumentation.py
harambe/meta.py
harambe/pagination.py
harambe/proxy.py
harambe/py.typed
harambe/tracker.py
harambe/types.py
harambe/user_agent.py
harambe/utils.py
harambe/contrib/__init__.py
harambe/contrib/types.py
harambe/contrib/playwright/__init__.py
harambe/contrib/playwright/harness.py
harambe/contrib/playwright/impl.py
harambe/contrib/soup/__init__.py
harambe/contrib/soup/harness.py
harambe/contrib/soup/impl.py
harambe/contrib/soup/tracing.py
harambe/html_converter/__init__.py
harambe/html_converter/html_to_markdown.py
harambe/html_converter/html_to_text.py
harambe_sdk-0.77.5.dist-info/METADATA
harambe_sdk-0.77.5.dist-info/WHEEL
harambe_sdk-0.77.5.dist-info/top_level.txt
harambe_sdk-0.77.5.dist-info/RECORD
