Metadata-Version: 2.4
Name: harambe-sdk
Version: 0.77.5
Summary: Data extraction SDK for Playwright 🐒🍌
Author-email: Adam Watkins <adam@reworkd.ai>
Requires-Python: <4.0,>=3.11
Requires-Dist: harambe_core==0.77.5
Requires-Dist: playwright==1.47.0
Requires-Dist: beautifulsoup4==4.12.3
Requires-Dist: requests==2.32.3
Requires-Dist: playwright-stealth==1.0.6
Requires-Dist: aiohttp==3.10.10
Requires-Dist: curl-cffi==0.7.3
Requires-Dist: ua-generator==1.0.5
Requires-Dist: markdownify==0.14.1
Requires-Dist: setuptools>=73.0.0
Requires-Dist: wrapt>=1.17.2
